[
  {
    "positie": 1,
    "club": "AFC 2",
    "logo": "images/afc.png",
    "gespeeld": 0,
    "gewonnen": 0,
    "gelijk": 0,
    "verloren": 0,
    "voor": 0,
    "tegen": 0,
    "doelsaldo": 0,
    "punten": 0
  },
  {
    "positie": 2,
    "club": "Almere FC 2",
    "logo": "",
    "gespeeld": 0,
    "gewonnen": 0,
    "gelijk": 0,
    "verloren": 0,
    "voor": 0,
    "tegen": 0,
    "doelsaldo": 0,
    "punten": 0
  },
  {
    "positie": 3,
    "club": "ASV Arsenal 2",
    "logo": "",
    "gespeeld": 0,
    "gewonnen": 0,
    "gelijk": 0,
    "verloren": 0,
    "voor": 0,
    "tegen": 0,
    "doelsaldo": 0,
    "punten": 0
  },
  {
    "positie": 4,
    "club": "Buitenboys sc. 2",
    "logo": "",
    "gespeeld": 0,
    "gewonnen": 0,
    "gelijk": 0,
    "verloren": 0,
    "voor": 0,
    "tegen": 0,
    "doelsaldo": 0,
    "punten": 0
  },
  {
    "positie": 5,
    "club": "CTO '70 vv 2",
    "logo": "",
    "gespeeld": 0,
    "gewonnen": 0,
    "gelijk": 0,
    "verloren": 0,
    "voor": 0,
    "tegen": 0,
    "doelsaldo": 0,
    "punten": 0
  },
  {
    "positie": 6,
    "club": "DTA Fortius asv 2",
    "logo": "images/fortius.png",
    "gespeeld": 0,
    "gewonnen": 0,
    "gelijk": 0,
    "verloren": 0,
    "voor": 0,
    "tegen": 0,
    "doelsaldo": 0,
    "punten": 0
  },
  {
    "positie": 7,
    "club": "DVVA csv. 3",
    "logo": "",
    "gespeeld": 0,
    "gewonnen": 0,
    "gelijk": 0,
    "verloren": 0,
    "voor": 0,
    "tegen": 0,
    "doelsaldo": 0,
    "punten": 0
  },
  {
    "positie": 8,
    "club": "SDO 2",
    "logo": "",
    "gespeeld": 0,
    "gewonnen": 0,
    "gelijk": 0,
    "verloren": 0,
    "voor": 0,
    "tegen": 0,
    "doelsaldo": 0,
    "punten": 0
  },
  {
    "positie": 9,
    "club": "Swift 4",
    "logo": "",
    "gespeeld": 0,
    "gewonnen": 0,
    "gelijk": 0,
    "verloren": 0,
    "voor": 0,
    "tegen": 0,
    "doelsaldo": 0,
    "punten": 0
  },
  {
    "positie": 10,
    "club": "Waterwijk asc 2",
    "logo": "",
    "gespeeld": 0,
    "gewonnen": 0,
    "gelijk": 0,
    "verloren": 0,
    "voor": 0,
    "tegen": 0,
    "doelsaldo": 0,
    "punten": 0
  },
  {
    "positie": 11,
    "club": "FC Weesp 2",
    "logo": "",
    "gespeeld": 0,
    "gewonnen": 0,
    "gelijk": 0,
    "verloren": 0,
    "voor": 0,
    "tegen": 0,
    "doelsaldo": 0,
    "punten": 0
  },
  {
    "positie": 12,
    "club": "Zuidoost United 2",
    "logo": "",
    "gespeeld": 0,
    "gewonnen": 0,
    "gelijk": 0,
    "verloren": 0,
    "voor": 0,
    "tegen": 0,
    "doelsaldo": 0,
    "punten": 0
  }
]