[
  {
    "id": 537447,
    "datum": "zo 10 augustus",
    "thuis": "Ajax",
    "thuisLogo": "https://crests.football-data.org/678.png",
    "uit": "Telstar 1963",
    "uitLogo": "https://crests.football-data.org/1912.png",
    "thuisScore": 2,
    "uitScore": 0
  },
  {
    "id": 537454,
    "datum": "zo 17 augustus",
    "thuis": "Go Ahead Eagles",
    "thuisLogo": "https://crests.football-data.org/718.png",
    "uit": "Ajax",
    "uitLogo": "https://crests.football-data.org/678.png",
    "thuisScore": 2,
    "uitScore": 2
  },
  {
    "id": 537466,
    "datum": "zo 24 augustus",
    "thuis": "Ajax",
    "thuisLogo": "https://crests.football-data.org/678.png",
    "uit": "Heracles",
    "uitLogo": "https://crests.football-data.org/671.png",
    "thuisScore": 2,
    "uitScore": 0
  },
  {
    "id": 537469,
    "datum": "za 30 augustus",
    "thuis": "FC Volendam",
    "thuisLogo": "https://crests.football-data.org/1919.png",
    "uit": "Ajax",
    "uitLogo": "https://crests.football-data.org/678.png",
    "thuisScore": 1,
    "uitScore": 1
  },
  {
    "id": 537477,
    "datum": "za 13 september",
    "thuis": "Ajax",
    "thuisLogo": "https://crests.football-data.org/678.png",
    "uit": "PEC Zwolle",
    "uitLogo": "https://crests.football-data.org/684.png",
    "thuisScore": 3,
    "uitScore": 1
  },
  {
    "id": 551936,
    "datum": "wo 17 september",
    "thuis": "Ajax",
    "thuisLogo": "https://crests.football-data.org/678.png",
    "uit": "FC Internazionale Milano",
    "uitLogo": "https://crests.football-data.org/108.png",
    "thuisScore": 0,
    "uitScore": 2
  },
  {
    "id": 537492,
    "datum": "zo 21 september",
    "thuis": "PSV",
    "thuisLogo": "https://crests.football-data.org/674.png",
    "uit": "Ajax",
    "uitLogo": "https://crests.football-data.org/678.png",
    "thuisScore": 2,
    "uitScore": 2
  },
  {
    "id": 537497,
    "datum": "za 27 september",
    "thuis": "Ajax",
    "thuisLogo": "https://crests.football-data.org/678.png",
    "uit": "NAC Breda",
    "uitLogo": "https://crests.football-data.org/681.png",
    "thuisScore": 2,
    "uitScore": 1
  },
  {
    "id": 552015,
    "datum": "di 30 september",
    "thuis": "Olympique de Marseille",
    "thuisLogo": "https://crests.football-data.org/516.png",
    "uit": "Ajax",
    "uitLogo": "https://crests.football-data.org/678.png",
    "thuisScore": 4,
    "uitScore": 0
  },
  {
    "id": 537505,
    "datum": "za 4 oktober",
    "thuis": "Sparta",
    "thuisLogo": "https://crests.football-data.org/6806.png",
    "uit": "Ajax",
    "uitLogo": "https://crests.football-data.org/678.png",
    "thuisScore": 3,
    "uitScore": 3
  },
  {
    "id": 537516,
    "datum": "za 18 oktober",
    "thuis": "Ajax",
    "thuisLogo": "https://crests.football-data.org/678.png",
    "uit": "AZ",
    "uitLogo": "https://crests.football-data.org/682.png",
    "thuisScore": 0,
    "uitScore": 2
  },
  {
    "id": 551919,
    "datum": "wo 22 oktober",
    "thuis": "Chelsea FC",
    "thuisLogo": "https://crests.football-data.org/61.png",
    "uit": "Ajax",
    "uitLogo": "https://crests.football-data.org/678.png",
    "thuisScore": 5,
    "uitScore": 1
  },
  {
    "id": 537527,
    "datum": "zo 26 oktober",
    "thuis": "FC Twente '65",
    "thuisLogo": "https://crests.football-data.org/666.png",
    "uit": "Ajax",
    "uitLogo": "https://crests.football-data.org/678.png",
    "thuisScore": 2,
    "uitScore": 3
  },
  {
    "id": 537534,
    "datum": "za 1 november",
    "thuis": "Ajax",
    "thuisLogo": "https://crests.football-data.org/678.png",
    "uit": "Heerenveen",
    "uitLogo": "https://crests.football-data.org/673.png",
    "thuisScore": 1,
    "uitScore": 1
  },
  {
    "id": 552033,
    "datum": "wo 5 november",
    "thuis": "Ajax",
    "thuisLogo": "https://crests.football-data.org/678.png",
    "uit": "Galatasaray SK",
    "uitLogo": "https://crests.football-data.org/610.png",
    "thuisScore": 0,
    "uitScore": 3
  },
  {
    "id": 537545,
    "datum": "zo 9 november",
    "thuis": "FC Utrecht",
    "thuisLogo": "https://crests.football-data.org/676.png",
    "uit": "Ajax",
    "uitLogo": "https://crests.football-data.org/678.png",
    "thuisScore": 2,
    "uitScore": 1
  },
  {
    "id": 537549,
    "datum": "za 22 november",
    "thuis": "Ajax",
    "thuisLogo": "https://crests.football-data.org/678.png",
    "uit": "SBV Excelsior",
    "uitLogo": "https://crests.football-data.org/670.png",
    "thuisScore": 1,
    "uitScore": 2
  },
  {
    "id": 551990,
    "datum": "di 25 november",
    "thuis": "Ajax",
    "thuisLogo": "https://crests.football-data.org/678.png",
    "uit": "Sport Lisboa e Benfica",
    "uitLogo": "https://crests.football-data.org/1903.png",
    "thuisScore": 0,
    "uitScore": 2
  },
  {
    "id": 537558,
    "datum": "di 2 december",
    "thuis": "Ajax",
    "thuisLogo": "https://crests.football-data.org/678.png",
    "uit": "Groningen",
    "uitLogo": "https://crests.football-data.org/677.png",
    "thuisScore": 2,
    "uitScore": 0
  },
  {
    "id": 537572,
    "datum": "za 6 december",
    "thuis": "Fortuna Sittard",
    "thuisLogo": "https://crests.football-data.org/1920.png",
    "uit": "Ajax",
    "uitLogo": "https://crests.football-data.org/678.png",
    "thuisScore": 1,
    "uitScore": 3
  },
  {
    "id": 552034,
    "datum": "wo 10 december",
    "thuis": "Qarabağ Ağdam FK",
    "thuisLogo": "https://crests.football-data.org/611.png",
    "uit": "Ajax",
    "uitLogo": "https://crests.football-data.org/678.png",
    "thuisScore": 2,
    "uitScore": 4
  },
  {
    "id": 537576,
    "datum": "zo 14 december",
    "thuis": "Ajax",
    "thuisLogo": "https://crests.football-data.org/678.png",
    "uit": "Feyenoord Rotterdam",
    "uitLogo": "https://crests.football-data.org/675.png",
    "thuisScore": 2,
    "uitScore": 0
  },
  {
    "id": 537593,
    "datum": "za 20 december",
    "thuis": "NEC",
    "thuisLogo": "https://crests.football-data.org/1915.png",
    "uit": "Ajax",
    "uitLogo": "https://crests.football-data.org/678.png",
    "thuisScore": 2,
    "uitScore": 2
  },
  {
    "id": 537601,
    "datum": "zo 11 januari",
    "thuis": "Telstar 1963",
    "thuisLogo": "https://crests.football-data.org/1912.png",
    "uit": "Ajax",
    "uitLogo": "https://crests.football-data.org/678.png",
    "thuisScore": 2,
    "uitScore": 3
  },
  {
    "id": 537603,
    "datum": "za 17 januari",
    "thuis": "Ajax",
    "thuisLogo": "https://crests.football-data.org/678.png",
    "uit": "Go Ahead Eagles",
    "uitLogo": "https://crests.football-data.org/718.png",
    "thuisScore": 2,
    "uitScore": 2
  },
  {
    "id": 552011,
    "datum": "di 20 januari",
    "thuis": "Villarreal CF",
    "thuisLogo": "https://crests.football-data.org/94.png",
    "uit": "Ajax",
    "uitLogo": "https://crests.football-data.org/678.png",
    "thuisScore": 1,
    "uitScore": 2
  },
  {
    "id": 537612,
    "datum": "za 24 januari",
    "thuis": "Ajax",
    "thuisLogo": "https://crests.football-data.org/678.png",
    "uit": "FC Volendam",
    "uitLogo": "https://crests.football-data.org/1919.png",
    "thuisScore": 2,
    "uitScore": 0
  },
  {
    "id": 552030,
    "datum": "wo 28 januari",
    "thuis": "Ajax",
    "thuisLogo": "https://crests.football-data.org/678.png",
    "uit": "PAE Olympiakos SFP",
    "uitLogo": "https://crests.football-data.org/654.png",
    "thuisScore": 1,
    "uitScore": 2
  },
  {
    "id": 537622,
    "datum": "zo 1 februari",
    "thuis": "SBV Excelsior",
    "thuisLogo": "https://crests.football-data.org/670.png",
    "uit": "Ajax",
    "uitLogo": "https://crests.football-data.org/678.png",
    "thuisScore": 2,
    "uitScore": 2
  },
  {
    "id": 537630,
    "datum": "zo 8 februari",
    "thuis": "AZ",
    "thuisLogo": "https://crests.football-data.org/682.png",
    "uit": "Ajax",
    "uitLogo": "https://crests.football-data.org/678.png",
    "thuisScore": 1,
    "uitScore": 1
  },
  {
    "id": 537639,
    "datum": "za 14 februari",
    "thuis": "Ajax",
    "thuisLogo": "https://crests.football-data.org/678.png",
    "uit": "Fortuna Sittard",
    "uitLogo": "https://crests.football-data.org/1920.png",
    "thuisScore": 4,
    "uitScore": 1
  },
  {
    "id": 537648,
    "datum": "za 21 februari",
    "thuis": "Ajax",
    "thuisLogo": "https://crests.football-data.org/678.png",
    "uit": "NEC",
    "uitLogo": "https://crests.football-data.org/1915.png",
    "thuisScore": 1,
    "uitScore": 1
  },
  {
    "id": 537662,
    "datum": "zo 1 maart",
    "thuis": "PEC Zwolle",
    "thuisLogo": "https://crests.football-data.org/684.png",
    "uit": "Ajax",
    "uitLogo": "https://crests.football-data.org/678.png",
    "thuisScore": 0,
    "uitScore": 0
  },
  {
    "id": 537667,
    "datum": "za 7 maart",
    "thuis": "Groningen",
    "thuisLogo": "https://crests.football-data.org/677.png",
    "uit": "Ajax",
    "uitLogo": "https://crests.football-data.org/678.png",
    "thuisScore": 3,
    "uitScore": 1
  },
  {
    "id": 537675,
    "datum": "za 14 maart",
    "thuis": "Ajax",
    "thuisLogo": "https://crests.football-data.org/678.png",
    "uit": "Sparta",
    "uitLogo": "https://crests.football-data.org/6806.png",
    "thuisScore": 4,
    "uitScore": 0
  },
  {
    "id": 537686,
    "datum": "zo 22 maart",
    "thuis": "Feyenoord Rotterdam",
    "thuisLogo": "https://crests.football-data.org/675.png",
    "uit": "Ajax",
    "uitLogo": "https://crests.football-data.org/678.png",
    "thuisScore": 1,
    "uitScore": 1
  },
  {
    "id": 537693,
    "datum": "za 4 april",
    "thuis": "Ajax",
    "thuisLogo": "https://crests.football-data.org/678.png",
    "uit": "FC Twente '65",
    "uitLogo": "https://crests.football-data.org/666.png",
    "thuisScore": 1,
    "uitScore": 2
  },
  {
    "id": 537706,
    "datum": "za 11 april",
    "thuis": "Heracles",
    "thuisLogo": "https://crests.football-data.org/671.png",
    "uit": "Ajax",
    "uitLogo": "https://crests.football-data.org/678.png",
    "thuisScore": 0,
    "uitScore": 3
  }
]